homopolymer_compression.cpython-36m-darwin.so
plasmidpredictor.cpython-36m-darwin.so
plasmidpredictor/Blocks.py
plasmidpredictor/Fasta.py
plasmidpredictor/Fastq.py
plasmidpredictor/Gene.py
plasmidpredictor/InputTypes.py
plasmidpredictor/Kmers.py
plasmidpredictor/PlasmidPredictor.py
plasmidpredictor/PlasmidPredictorDatabaseDownloader.py
plasmidpredictor/Read.py
plasmidpredictor/RefGenesGetter.py
plasmidpredictor/__init__.py
plasmidpredictor/data/20180405.txt
plasmidpredictor/data/plasmid_data.fa
plasmidpredictor/data/plasmid_data.tsv
plasmidpredictor-0.1.0.data/scripts/plasmidpredictor
plasmidpredictor-0.1.0.data/scripts/plasmidpredictor_database_downloader
plasmidpredictor-0.1.0.dist-info/DESCRIPTION.rst
plasmidpredictor-0.1.0.dist-info/METADATA
plasmidpredictor-0.1.0.dist-info/RECORD
plasmidpredictor-0.1.0.dist-info/WHEEL
plasmidpredictor-0.1.0.dist-info/metadata.json
plasmidpredictor-0.1.0.dist-info/top_level.txt
